wecrypt/__init__.py
wecrypt-0.0.1.dist-info/WHEEL
wecrypt-0.0.1.dist-info/METADATA
wecrypt-0.0.1.dist-info/RECORD
